{
    "问题类型": {
        "开放性问题": [
            "社会责任",
            "客户集中度",
            "同行业"
        ],
        "财务问题": [
            "资产负债比率",
            "研发经费",
            "利润",
            "现金及现金等价物",
            "投资收益",
            "财务费用",
            "营业利润率",
            "管理费用",
            "应付职工薪酬",
            "销售费用",
            "营业收入",
            "归属于上市公司股东的净利润",
            "归属于上市公司股东的扣除非经常性损益的净利润",
            "经营活动产生的现金流量净额",
            "基本每股收益",
            "稀释每股收益",
            "加权平均净资产收益率",
            "资产总额",
            "归属于上市公司股东的净资产",
            "归属于上市公司股东的净利润",
            "归属于上市公司股东的扣除非经常性损益的净利润",
            "经营活动产生的现金流量净额",
            "股权资产",
            "固定资产",
            "无形资产",
            "在建工程",
            "速动比率",
            "现金比率",
            "货币资金", 
            "短期投资", 
            "应收利息",
            "应收股利", 
            "应收账款", 
            "预付账款", 
            "应收补贴款", 
            "存货", 
            "待摊费用", 
            "长期股权投资", 
            "长期债权投资", 
            "固定资产", 
            "工程物资", 
            "在建工程", 
            "固定资产清理", 
            "无形资产", 
            "长期待摊费用",
            "综合收益总额",
            "应收款项融资",
            "衍生金融资产",
            "其他非流动金融资产",
            "公允价值变动收益",
            "净利润增长率",
            "现金比率"
        ],
        "人员问题": [
            "博士",
            "硕士",
            "本科",
            "法定代表人"
        ],
        "基本信息": [
            "电子信箱",
            "企业名称",
            "办公地址"
        ]
    }, "问题等级": {
        "第二类": [
            "增长率",
            "比值"
        ]
    }
}